aliyun_log_fastpb-0.2.0.dist-info/METADATA
aliyun_log_fastpb-0.2.0.dist-info/WHEEL
aliyun_log_fastpb-0.2.0.dist-info/licenses/LICENSE
aliyun_log_fastpb.libs/libgcc_s-98a1ef30.so.1
aliyun_log_fastpb/__init__.py
aliyun_log_fastpb/__init__.pyi
aliyun_log_fastpb/aliyun_log_fastpb.abi3.so
aliyun_log_fastpb/py.typed
aliyun_log_fastpb-0.2.0.dist-info/RECORD
